[{"data":{"menu":"","index":"","linkheadings":0,"tableOfContents":[]},"filename":"avaliacoes.md","id":"avaliacoes","label":"Avaliacoes","imports":[],"outputPath":"/documentos/avaliacoes/index.html","path":"src/pages/documentos/avaliacoes.md","route":"/documentos/avaliacoes/","template":"page","title":"Avaliações","isSSR":false},{"data":{"menu":"","index":"","linkheadings":0,"tableOfContents":[]},"filename":"calendario.md","id":"calendario","label":"Calendario","imports":[],"outputPath":"/documentos/calendario/index.html","path":"src/pages/documentos/calendario.md","route":"/documentos/calendario/","template":"page","title":"Calendário","isSSR":false},{"data":{"menu":"","index":"","linkheadings":0,"tableOfContents":[]},"filename":"reunioes.md","id":"reunioes","label":"Reunioes","imports":[],"outputPath":"/documentos/reunioes/index.html","path":"src/pages/documentos/reunioes.md","route":"/documentos/reunioes/","template":"page","title":"Reuniões","isSSR":false},{"data":{"menu":"","index":"","linkheadings":0,"tableOfContents":[]},"filename":"documentos.html","id":"documentos","label":"Documentos","imports":[],"outputPath":"/documentos/index.html","path":"src/pages/documentos.html","route":"/documentos/","template":"page","title":null,"isSSR":false},{"data":{"menu":"","index":"","linkheadings":0,"tableOfContents":[]},"filename":"index.html","id":"index","label":"Index","imports":[],"outputPath":"/index.html","path":"src/pages/index.html","route":"/","template":"page","title":null,"isSSR":false},{"data":{"status":"ativo","name":"Ana Julia Trindade","img":"https://avatars.githubusercontent.com/u/104458133?v=4","menu":"","index":"","linkheadings":0,"tableOfContents":[]},"filename":"ana-julia.md","id":"ana-julia","label":"Ana Julia","imports":[],"outputPath":"/membros/ana-julia/index.html","path":"src/pages/membros/ana-julia.md","route":"/membros/ana-julia/","template":"page","title":null,"isSSR":false},{"data":{"status":"ativo","name":"André Augusto","img":"https://avatars.githubusercontent.com/u/77406727?v=4","menu":"","index":"","linkheadings":0,"tableOfContents":[]},"filename":"andre-augusto.md","id":"andre-augusto","label":"Andre Augusto","imports":[],"outputPath":"/membros/andre-augusto/index.html","path":"src/pages/membros/andre-augusto.md","route":"/membros/andre-augusto/","template":"page","title":null,"isSSR":false},{"data":{"status":"desativado","name":"Bruno Joshua Medeiros","way":"/membros/bruno-joshua","menu":"","index":"","linkheadings":0,"tableOfContents":[]},"filename":"bruno-joshua.md","id":"bruno-joshua","label":"Bruno Joshua","imports":[],"outputPath":"/membros/bruno-joshua/index.html","path":"src/pages/membros/bruno-joshua.md","route":"/membros/bruno-joshua/","template":"page","title":null,"isSSR":false},{"data":{"status":"desativado","name":"Carlos Silva","img":"https://avatars.githubusercontent.com/u/10880779?v=4","way":"/membros/carlos-silva","menu":"","index":"","linkheadings":0,"tableOfContents":[]},"filename":"carlos-silva.md","id":"carlos-silva","label":"Carlos Silva","imports":[],"outputPath":"/membros/carlos-silva/index.html","path":"src/pages/membros/carlos-silva.md","route":"/membros/carlos-silva/","template":"page","title":null,"isSSR":false},{"data":{"status":"ativo","name":"Danilo Bueno","img":"https://avatars.githubusercontent.com/u/2002182?v=4","way":"/membros/danilao","menu":"","index":"","linkheadings":0,"tableOfContents":[]},"filename":"danilao.md","id":"danilao","label":"Danilao","imports":[],"outputPath":"/membros/danilao/index.html","path":"src/pages/membros/danilao.md","route":"/membros/danilao/","template":"page","title":null,"isSSR":false},{"data":{"status":"ativo","name":"Gabriel Machado","img":"https://avatars.githubusercontent.com/u/103156444?v=4","menu":"","index":"","linkheadings":0,"tableOfContents":[]},"filename":"gabriel-machado.md","id":"gabriel-machado","label":"Gabriel Machado","imports":[],"outputPath":"/membros/gabriel-machado/index.html","path":"src/pages/membros/gabriel-machado.md","route":"/membros/gabriel-machado/","template":"page","title":null,"isSSR":false},{"data":{"status":"ativo","name":"João Corrêa","img":"https://avatars.githubusercontent.com/u/75680576?v=4","menu":"","index":"","linkheadings":0,"tableOfContents":[]},"filename":"joao-correa.md","id":"joao-correa","label":"Joao Correa","imports":[],"outputPath":"/membros/joao-correa/index.html","path":"src/pages/membros/joao-correa.md","route":"/membros/joao-correa/","template":"page","title":null,"isSSR":false},{"data":{"status":"desativado","name":"João Morais","img":"https://avatars.githubusercontent.com/u/41636783?v=4","way":"/membros/joao-morais","menu":"","index":"","linkheadings":0,"tableOfContents":[]},"filename":"joao-morais.md","id":"joao-morais","label":"Joao Morais","imports":[],"outputPath":"/membros/joao-morais/index.html","path":"src/pages/membros/joao-morais.md","route":"/membros/joao-morais/","template":"page","title":null,"isSSR":false},{"data":{"status":"desativado","name":"Laura Naomi","img":"https://avatars.githubusercontent.com/u/47746453?v=4","way":"/membros/laura-naomi","menu":"","index":"","linkheadings":0,"tableOfContents":[]},"filename":"laura-naomi.md","id":"laura-naomi","label":"Laura Naomi","imports":[],"outputPath":"/membros/laura-naomi/index.html","path":"src/pages/membros/laura-naomi.md","route":"/membros/laura-naomi/","template":"page","title":null,"isSSR":false},{"data":{"status":"desativado","name":"Lucas Cavalherie","img":"https://avatars.githubusercontent.com/u/41579591?v=4","way":"/membros/lucas-cavalherie","menu":"","index":"","linkheadings":0,"tableOfContents":[]},"filename":"lucas-cavalherie.md","id":"lucas-cavalherie","label":"Lucas Cavalherie","imports":[],"outputPath":"/membros/lucas-cavalherie/index.html","path":"src/pages/membros/lucas-cavalherie.md","route":"/membros/lucas-cavalherie/","template":"page","title":null,"isSSR":false},{"data":{"status":"desativado","name":"Maria Eduarda Senger","img":"https://avatars.githubusercontent.com/u/77407513?v=4","way":"/membros/maria-senger","menu":"","index":"","linkheadings":0,"tableOfContents":[]},"filename":"maria-senger.md","id":"maria-senger","label":"Maria Senger","imports":[],"outputPath":"/membros/maria-senger/index.html","path":"src/pages/membros/maria-senger.md","route":"/membros/maria-senger/","template":"page","title":null,"isSSR":false},{"data":{"status":"desativado","name":"Neemias Matos","img":"https://avatars.githubusercontent.com/u/51499704?v=4","way":"/membros/neemias-matos","menu":"","index":"","linkheadings":0,"tableOfContents":[]},"filename":"neemias-matos.md","id":"neemias-matos","label":"Neemias Matos","imports":[],"outputPath":"/membros/neemias-matos/index.html","path":"src/pages/membros/neemias-matos.md","route":"/membros/neemias-matos/","template":"page","title":null,"isSSR":false},{"data":{"status":"desativado","name":"Pedro Gois","img":"https://avatars.githubusercontent.com/u/41579818?v=4","way":"/membros/pedro-gois","menu":"","index":"","linkheadings":0,"tableOfContents":[]},"filename":"pedro-gois.md","id":"pedro-gois","label":"Pedro Gois","imports":[],"outputPath":"/membros/pedro-gois/index.html","path":"src/pages/membros/pedro-gois.md","route":"/membros/pedro-gois/","template":"page","title":null,"isSSR":false},{"data":{"status":"ativo","name":"Rafael Alexandre","img":"https://avatars.githubusercontent.com/u/77407339?v=4","menu":"","index":"","linkheadings":0,"tableOfContents":[]},"filename":"rafael-alexandre.md","id":"rafael-alexandre","label":"Rafael Alexandre","imports":[],"outputPath":"/membros/rafael-alexandre/index.html","path":"src/pages/membros/rafael-alexandre.md","route":"/membros/rafael-alexandre/","template":"page","title":null,"isSSR":false},{"data":{"status":"desativado","name":"Rafael Brochado","way":"/membros/rafael-brochado","menu":"","index":"","linkheadings":0,"tableOfContents":[]},"filename":"rafael-brochado.md","id":"rafael-brochado","label":"Rafael Brochado","imports":[],"outputPath":"/membros/rafael-brochado/index.html","path":"src/pages/membros/rafael-brochado.md","route":"/membros/rafael-brochado/","template":"page","title":null,"isSSR":false},{"data":{"status":"desativado","name":"Rafael Santos","img":"https://avatars.githubusercontent.com/u/41579736?v=4","way":"/membros/rafael-santos","menu":"","index":"","linkheadings":0,"tableOfContents":[]},"filename":"rafael-santos.md","id":"rafael-santos","label":"Rafael Santos","imports":[],"outputPath":"/membros/rafael-santos/index.html","path":"src/pages/membros/rafael-santos.md","route":"/membros/rafael-santos/","template":"page","title":null,"isSSR":false},{"data":{"status":"desativado","name":"Samuel Facchetti","img":"https://avatars.githubusercontent.com/u/47745205?v=4","way":"/membros/samuel-matos","menu":"","index":"","linkheadings":0,"tableOfContents":[]},"filename":"samuel-matos.md","id":"samuel-matos","label":"Samuel Matos","imports":[],"outputPath":"/membros/samuel-matos/index.html","path":"src/pages/membros/samuel-matos.md","route":"/membros/samuel-matos/","template":"page","title":null,"isSSR":false},{"data":{"status":"ativo","name":"Vinícius Manoel","img":"https://avatars.githubusercontent.com/u/103225663?v=4","menu":"","index":"","linkheadings":0,"tableOfContents":[]},"filename":"vinicius-manoel.md","id":"vinicius-manoel","label":"Vinicius Manoel","imports":[],"outputPath":"/membros/vinicius-manoel/index.html","path":"src/pages/membros/vinicius-manoel.md","route":"/membros/vinicius-manoel/","template":"page","title":null,"isSSR":false},{"data":{"status":"desativado","name":"Vinicius Zevarex","img":"https://avatars.githubusercontent.com/u/41579743?v=4","way":"/membros/vinicius-zeravex","menu":"","index":"","linkheadings":0,"tableOfContents":[]},"filename":"vinicius-zeravex.md","id":"vinicius-zeravex","label":"Vinicius Zeravex","imports":[],"outputPath":"/membros/vinicius-zeravex/index.html","path":"src/pages/membros/vinicius-zeravex.md","route":"/membros/vinicius-zeravex/","template":"page","title":null,"isSSR":false},{"data":{"status":"ativo","name":"Vitor Gabriel de Aquino","img":"https://avatars.githubusercontent.com/u/95290697?v=4","menu":"","index":"","linkheadings":0,"tableOfContents":[]},"filename":"vitor-aquino.md","id":"vitor-aquino","label":"Vitor Aquino","imports":[],"outputPath":"/membros/vitor-aquino/index.html","path":"src/pages/membros/vitor-aquino.md","route":"/membros/vitor-aquino/","template":"page","title":null,"isSSR":false},{"data":{"menu":"","index":"","linkheadings":0,"tableOfContents":[]},"filename":"membros.html","id":"membros","label":"Membros","imports":[],"outputPath":"/membros/index.html","path":"src/pages/membros.html","route":"/membros/","template":"page","title":null,"isSSR":false},{"data":{"img":"/assets/projetos/logo-consultorio-na-rua.jpg","menu":"","index":"","linkheadings":0,"tableOfContents":[]},"filename":"consultorio-na-rua.md","id":"consultorio-na-rua","label":"Consultorio Na Rua","imports":[],"outputPath":"/projetos/consultorio-na-rua/index.html","path":"src/pages/projetos/consultorio-na-rua.md","route":"/projetos/consultorio-na-rua/","template":"page","title":"App do Consultório na Rua","isSSR":false},{"data":{"img":"/assets/projetos/logo-show-de-fisica.jpg","menu":"","index":"","linkheadings":0,"tableOfContents":[]},"filename":"show-de-fisica.md","id":"show-de-fisica","label":"Show De Fisica","imports":[],"outputPath":"/projetos/show-de-fisica/index.html","path":"src/pages/projetos/show-de-fisica.md","route":"/projetos/show-de-fisica/","template":"page","title":"Show de Física","isSSR":false},{"data":{"img":"/assets/projetos/logo-sge.png","menu":"","index":"","linkheadings":0,"tableOfContents":[]},"filename":"sis-gerenciamento-de-eventos.md","id":"sis-gerenciamento-de-eventos","label":"Sis Gerenciamento De Eventos","imports":[],"outputPath":"/projetos/sis-gerenciamento-de-eventos/index.html","path":"src/pages/projetos/sis-gerenciamento-de-eventos.md","route":"/projetos/sis-gerenciamento-de-eventos/","template":"page","title":"SGE - Sistema de Gerenciamento de Eventos","isSSR":false},{"data":{"img":"/assets/projetos/logo-espweb.png","menu":"","index":"","linkheadings":0,"tableOfContents":[]},"filename":"site-espweb.md","id":"site-espweb","label":"Site Espweb","imports":[],"outputPath":"/projetos/site-espweb/index.html","path":"src/pages/projetos/site-espweb.md","route":"/projetos/site-espweb/","template":"page","title":"Site Especialização em Desenvolvimento Web","isSSR":false},{"data":{"img":"/assets/projetos/logo-svsa.png","menu":"","index":"","linkheadings":0,"tableOfContents":[]},"filename":"svsa-manual.md","id":"svsa-manual","label":"Svsa Manual","imports":[],"outputPath":"/projetos/svsa-manual/index.html","path":"src/pages/projetos/svsa-manual.md","route":"/projetos/svsa-manual/","template":"page","title":"Manual do Usuário do SVSA","isSSR":false},{"data":{"menu":"","index":"","linkheadings":0,"tableOfContents":[]},"filename":"projetos.html","id":"projetos","label":"Projetos","imports":[],"outputPath":"/projetos/index.html","path":"src/pages/projetos.html","route":"/projetos/","template":"page","title":null,"isSSR":false},{"data":{"menu":"","index":"","linkheadings":0,"tableOfContents":[]},"filename":"sobre.html","id":"sobre","label":"Sobre","imports":[],"outputPath":"/sobre/index.html","path":"src/pages/sobre.html","route":"/sobre/","template":"page","title":null,"isSSR":false},{"data":{"extends":"_layouts.treina","section":"content","name":"Bootstrap","menu":"","index":"","linkheadings":0,"tableOfContents":[]},"filename":"bootstrap.md","id":"bootstrap","label":"Bootstrap","imports":[],"outputPath":"/treinamento/bootstrap/index.html","path":"src/pages/treinamento/bootstrap.md","route":"/treinamento/bootstrap/","template":"page","title":null,"isSSR":false},{"data":{"extends":"_layouts.treina","section":"content","name":"Figma","menu":"","index":"","linkheadings":0,"tableOfContents":[]},"filename":"figma.md","id":"figma","label":"Figma","imports":[],"outputPath":"/treinamento/figma/index.html","path":"src/pages/treinamento/figma.md","route":"/treinamento/figma/","template":"page","title":null,"isSSR":false},{"data":{"extends":"_layouts.treina","section":"content","name":"Git e Github","menu":"","index":"","linkheadings":0,"tableOfContents":[]},"filename":"github.md","id":"github","label":"Github","imports":[],"outputPath":"/treinamento/github/index.html","path":"src/pages/treinamento/github.md","route":"/treinamento/github/","template":"page","title":null,"isSSR":false},{"data":{"extends":"_layouts.treina","section":"content","name":"Laravel","menu":"","index":"","linkheadings":0,"tableOfContents":[]},"filename":"laravel.md","id":"laravel","label":"Laravel","imports":[],"outputPath":"/treinamento/laravel/index.html","path":"src/pages/treinamento/laravel.md","route":"/treinamento/laravel/","template":"page","title":null,"isSSR":false},{"data":{"author":"Vitor Gabriel de Aquino","name":"Manual do WebServer","menu":"","index":"","linkheadings":0,"tableOfContents":[]},"filename":"manual-server.md","id":"manual-server","label":"Manual Server","imports":[],"outputPath":"/treinamento/manual-server/index.html","path":"src/pages/treinamento/manual-server.md","route":"/treinamento/manual-server/","template":"page","title":"Manual de acesso ao WebServer","isSSR":false},{"data":{"extends":"_layouts.treina","section":"content","name":"Nuxt.js","menu":"","index":"","linkheadings":0,"tableOfContents":[]},"filename":"nuxt.md","id":"nuxt","label":"Nuxt","imports":[],"outputPath":"/treinamento/nuxt/index.html","path":"src/pages/treinamento/nuxt.md","route":"/treinamento/nuxt/","template":"page","title":null,"isSSR":false},{"data":{"extends":"_layouts.treina","section":"content","name":"Vue.js","menu":"","index":"","linkheadings":0,"tableOfContents":[]},"filename":"vue.md","id":"vue","label":"Vue","imports":[],"outputPath":"/treinamento/vue/index.html","path":"src/pages/treinamento/vue.md","route":"/treinamento/vue/","template":"page","title":null,"isSSR":false},{"data":{"menu":"","index":"","linkheadings":0,"tableOfContents":[]},"filename":"treinamento.html","id":"treinamento","label":"Treinamento","imports":[],"outputPath":"/treinamento/index.html","path":"src/pages/treinamento.html","route":"/treinamento/","template":"page","title":null,"isSSR":false},{"outputPath":"404.html","filename":"404.html","path":"404.html","route":"/404/","id":"404","label":"Not Found","data":{},"imports":[]}]